bankruptcy/__init__.py
bankruptcy/fields.py
bankruptcy/filters.py
bankruptcy/parser.py
bankruptcy/utils.py
test/__init__.py
test/tests.py
bankruptcy-0.0.7.dist-info/LICENSE
bankruptcy-0.0.7.dist-info/METADATA
bankruptcy-0.0.7.dist-info/WHEEL
bankruptcy-0.0.7.dist-info/top_level.txt
bankruptcy-0.0.7.dist-info/RECORD
