Metadata-Version: 2.1
Name: bankruptcy
Version: 0.0.7
Summary: A bankruptcy document parser.
Home-page: https://github.com/freelawproject/bankruptcy-parser
Author: Free Law Project
Author-email: info@free.law
Maintainer: Free Law Project
Maintainer-email: info@free.law
License: BSD
Keywords: legal,document,bankruptcy,PDF,form
Platform: UNKNOWN
Classifier: Development Status :: 5 - Production/Stable
Classifier: Intended Audience :: Developers
Classifier: Natural Language :: English
Classifier: License :: OSI Approved :: BSD License
Classifier: Operating System :: OS Independent
Classifier: Programming Language :: Python
Classifier: Programming Language :: Python :: 3
Classifier: Programming Language :: Python :: 3.7
Classifier: Programming Language :: Python :: 3.8
Classifier: Programming Language :: Python :: 3.9
Classifier: Programming Language :: Python :: 3.10
Classifier: Programming Language :: Python :: Implementation :: CPython
Classifier: Programming Language :: Python :: Implementation :: PyPy
Classifier: Topic :: Software Development :: Libraries :: Python Modules
License-File: LICENSE
Requires-Dist: Jinja2
Requires-Dist: pdfminer.six (>=20211012)
Requires-Dist: pdfplumber (>=0.6.0)
Requires-Dist: Pillow
Requires-Dist: PyPDF2 (==1.26.0)
Requires-Dist: regex (==2020.11.13)
Requires-Dist: six
Requires-Dist: sortedcontainers (==2.3.0)
Requires-Dist: Wand (>=0.6.7)
